{"season":14,"name":"Dude, Where's My Ranch?","year":"2003","rated":"TV-PG","released":null,"episode":18,"runtime":"30 min","genres":"Animation, Comedy","director":"Chris Clements","writer":"Matt Groening (created by), James L. Brooks (developed by), Matt Groening (developed by), Sam Simon (developed by), Ian Maxtone-Graham","actors":"Dan Castellaneta, Julie Kavner, Nancy Cartwright, Yeardley Smith","plot":"Homer writes a hit song,'Everybody Hates Ned Flanders' but the resultant publicity forces the family to flee the town and stay at the Lazy I Ranch,where Homer and Bart destroy a beavers' dam in order for native Americans to reclaim their land and Lisa falls for cowboy Luke Stetson. In fact Lisa's mistaken view that a girl called Clara,in reality Luke's sister,is her love rival,causes her to almost send Clara to a watery grave though Bart gets the beavers to - inadvertently - rescue her.","languages":"English","country":"USA","awards":"N/A","poster":"http://ia.media-imdb.com/images/M/MV5BMjM3Mjk1NDg0M15BMl5BanBnXkFtZTgwODM4NTQ2MjE@._V1_SX300.jpg","ratings":[{"Source":"Internet Movie Database","Value":"7.0/10"}],"metascore":"N/A","rating":"7.0","votes":"594","imdbid":"tt0701090","seriesid":"tt0096697","type":"episode","response":"True"}