{"season":7,"name":"The Naked Truth","year":"2011","rated":"TV-14","released":null,"episode":2,"runtime":"22 min","genres":"Comedy, Romance","director":"Pamela Fryman","writer":"Carter Bays (created by), Craig Thomas (created by), Stephen Lloyd, Craig Gerard (story editor), Matthew Zinman (story editor), Dan Gregor (story editor), Doug Mand (story editor)","actors":"Josh Radnor, Jason Segel, Cobie Smulders, Neil Patrick Harris","plot":"Ted tries to choose a date for the Architect's Ball, an embarrassing Internet video could cost Marshall a new job, and Barney makes a bold move to prove to Nora that he's a changed man.","languages":"English","country":"USA","awards":"N/A","poster":"http://ia.media-imdb.com/images/M/MV5BMTc2OTQyNjA4Nl5BMl5BanBnXkFtZTgwMTA4MDMyMjE@._V1_SX300.jpg","ratings":[{"Source":"Internet Movie Database","Value":"8.2/10"}],"metascore":"N/A","rating":"8.2","votes":"1630","imdbid":"tt2039807","seriesid":"tt0460649","type":"episode","response":"True"}