{"season":4,"name":"The Fight","year":"2008","rated":"TV-14","released":null,"episode":10,"runtime":"22 min","genres":"Comedy, Romance","director":"Pamela Fryman","writer":"Carter Bays (created by), Carter Bays (creator), Craig Thomas (created by), Craig Thomas (creator), Theresa Mulligan, Joe Kelly (executive story editor), Robia Rashid (story editor)","actors":"Josh Radnor, Jason Segel, Cobie Smulders, Neil Patrick Harris","plot":"The guys get invited to fight alongside Doug the Bartender. However, the fight doesn't go exactly how they imagined it to.","languages":"English","country":"USA","awards":"N/A","poster":"https://images-na.ssl-images-amazon.com/images/M/MV5BMTc0MzUyOTk0NF5BMl5BanBnXkFtZTcwNDA2OTUxMg@@._V1_SX300.jpg","ratings":[{"Source":"Internet Movie Database","Value":"8.4/10"}],"metascore":"N/A","rating":"8.4","votes":"1585","imdbid":"tt1256171","seriesid":"tt0460649","type":"episode","response":"True"}