{"season":3,"name":"Everything Must Go","year":"2008","rated":"TV-14","released":null,"episode":19,"runtime":"22 min","genres":"Comedy, Romance","director":"Pamela Fryman","writer":"Carter Bays (created by), Carter Bays (creator), Craig Thomas (created by), Craig Thomas (creator), Jonathan Groff, Chris Harris, Joe Kelly (executive story editor)","actors":"Josh Radnor, Jason Segel, Cobie Smulders, Neil Patrick Harris","plot":"Since Marshall and Lilly cannot afford the cost to level the floors of their new place, Marshall proposes its time to start selling some of Lilly's designer clothes. Lilly instead wants to make the money selling her paintings which takes her to some low places. Ted tries for an interesting look while Barney finally meets the girl that has been ruining his chance with women.","languages":"English","country":"USA","awards":"N/A","poster":"https://images-na.ssl-images-amazon.com/images/M/MV5BMTgzNjUyODM5MF5BMl5BanBnXkFtZTgwNzM5MDMyMjE@._V1_SX300.jpg","ratings":[{"Source":"Internet Movie Database","Value":"7.9/10"}],"metascore":"N/A","rating":"7.9","votes":"1755","imdbid":"tt1206870","seriesid":"tt0460649","type":"episode","response":"True"}