{"season":24,"name":"What Animated Women Want","year":"2013","rated":"TV-PG","released":null,"episode":17,"runtime":"30 min","genres":"Animation, Comedy","director":"Steven Dean Moore","writer":"Matt Groening (created by), James L. Brooks (developed by), Matt Groening (developed by), Sam Simon (developed by), J. Stewart Burns, Jon Kern (staff writer)","actors":"Dan Castellaneta, Julie Kavner, Nancy Cartwright, Yeardley Smith","plot":"Once more Homer's selfishness has antagonized Marge and his attempts to make things up with her consistently fail - until he resorts to buying sex toys, one of which injures him. They fail to impress her but she is pleased that he made the effort. Meanwhile, having watched 'A Streetcar Named Desire' Milhouse decides that the best way to court Lisa is to treat her mean though the façade eventually crumbles.","languages":"English","country":"USA","awards":"N/A","poster":"http://ia.media-imdb.com/images/M/MV5BMjA0Mjc5NzkwMF5BMl5BanBnXkFtZTcwOTQ1MTgzOQ@@._V1_SX300.jpg","ratings":[{"Source":"Internet Movie Database","Value":"6.5/10"}],"metascore":"N/A","rating":"6.5","votes":"388","imdbid":"tt2778778","seriesid":"tt0096697","type":"episode","response":"True"}