{"season":5,"name":"The Boy Who Knew Too Much","year":"1994","rated":"TV-14","released":null,"episode":20,"runtime":"30 min","genres":"Animation, Comedy","director":"Jeffrey Lynch","writer":"Matt Groening (created by), James L. Brooks (developed by), Matt Groening (developed by), Sam Simon (developed by), John Swartzwelder, Bill Canterbury (staff writer), David X. Cohen (staff writer)","actors":"Dan Castellaneta, Julie Kavner, Nancy Cartwright, Yeardley Smith","plot":"After playing hooky from school, Bart sneaks in to Mayor Quimby's nephew Freddy's birthday party and witnesses a confrontation between Freddy and a waiter, Freddy is accused of beating the waiter but Bart knows what really happened, should he keep quiet or tell the truth and risk getting Cort playing hooky?","languages":"English, Ukrainian","country":"USA","awards":"N/A","poster":"http://ia.media-imdb.com/images/M/MV5BMTk0MTAzMzgxOV5BMl5BanBnXkFtZTgwOTM3Mjg4MzE@._V1_SX300.jpg","ratings":[{"Source":"Internet Movie Database","Value":"8.2/10"}],"metascore":"N/A","rating":"8.2","votes":"1017","imdbid":"tt0778453","seriesid":"tt0096697","type":"episode","response":"True"}