{"season":14,"name":"A Star Is Born Again","year":"2003","rated":"TV-PG","released":null,"episode":13,"runtime":"30 min","genres":"Animation, Comedy","director":"Michael Marcantel","writer":"Matt Groening (created by), James L. Brooks (developed by), Matt Groening (developed by), Sam Simon (developed by), Brian Kelley","actors":"Dan Castellaneta, Julie Kavner, Nancy Cartwright, Yeardley Smith","plot":"Hollywood film star Sara Sloane is making a movie in Springfield and, after visiting his shop, becomes attracted to Ned Flanders, who starts dating her. Ned is reluctant to move to Hollywood so Sara blends in with the Springfield set but she eventually goes back to Tinseltown, having turned down Ned's marriage proposal. As a result however, Ned has become much more popular with the ladies.","languages":"English","country":"USA","awards":"N/A","poster":"http://ia.media-imdb.com/images/M/MV5BMTk0MTAzMzgxOV5BMl5BanBnXkFtZTgwOTM3Mjg4MzE@._V1_SX300.jpg","ratings":[{"Source":"Internet Movie Database","Value":"7.0/10"}],"metascore":"N/A","rating":"7.0","votes":"543","imdbid":"tt0701046","seriesid":"tt0096697","type":"episode","response":"True"}